TallyTools/__init__.py
TallyTools/checkers.py
TallyTools/operations.py
TallyTools/to_int.py
TallyTools/to_tally.py
TallyTools/utils.py
tallytools-0.1.0.dist-info/licenses/LICENSE.txt
tallytools-0.1.0.dist-info/METADATA
tallytools-0.1.0.dist-info/WHEEL
tallytools-0.1.0.dist-info/top_level.txt
tallytools-0.1.0.dist-info/RECORD
