Metadata-Version: 2.4
Name: TallyTools
Version: 0.1.0
Summary: A Python utility library for converting, validating, and performing arithmetic with tally marks.
Home-page: https://github.com/rishikeshgmahajan/TallyTools
Author: Rishikesh Mahajan
Author-email: Rishikesh Mahajan <rishimahajan2410@gmail.com>
License: MIT
Project-URL: Homepage, https://github.com/rishikeshgmahajan/TallyTools
Project-URL: Bug Tracker, https://github.com/rishikeshgmahajan/TallyTools/issues
Classifier: Programming Language :: Python :: 3
Classifier: License :: OSI Approved :: MIT License
Classifier: Operating System :: OS Independent
Requires-Python: >=3.6
License-File: LICENSE.txt
Dynamic: author
Dynamic: home-page
Dynamic: license-file
Dynamic: requires-python
